<?xml version="1.0" encoding="GB18030" standalone="no"?>
<!DOCTYPE log SYSTEM "logger.dtd">
<log>
<record>
  <date>2008-03-10T10:56:47</date>
  <millis>1205117807578</millis>
  <sequence>1</sequence>
  <logger>geoinformatics.nju.edu.cn</logger>
  <level>INFO</level>
  <class>ftp.FtpCrawler</class>
  <method>crawl</method>
  <thread>11</thread>
  <message>Start crawling ftp://geoinformatics.nju.edu.cn...</message>
</record>
<record>
  <date>2008-03-10T10:56:47</date>
  <millis>1205117807656</millis>
  <sequence>10</sequence>
  <logger>geoinformatics.nju.edu.cn</logger>
  <level>INFO</level>
  <class>ftp.FtpCrawler</class>
  <method>crawl</method>
  <thread>11</thread>
  <message>geoinformatics.nju.edu.cn connected: 220-------==== Welcome to Geoinformatics@NJU FTP Server ====------
220-          03090702・010208 0203060807ó05§080108í04030304070405§0308 FTP・06020904÷
220-
220-              04050203070103§02010104・01020805é0707020204060904±í
220-              0300080105050701090803§0502gis0502gis
220-                        03ò0908download0502download
220-       incomingfiles0207000407070608070307000202040605010403040302ú0802×080807010503í0503
220-           030501040909080706070209080108í04030304070405§°0302010908080200ì0001
220-
220-
220-                Administrator: WickerPark
220-         Please Contact WickerPark at BBS.NJU.EDU.CN
220-
220 -------==== Welcome to Geoinformatics@NJU FTP Server ====------------------
</message>
</record>
<record>
  <date>2008-03-10T10:56:47</date>
  <millis>1205117807656</millis>
  <sequence>12</sequence>
  <logger>geoinformatics.nju.edu.cn</logger>
  <level>INFO</level>
  <class>ftp.FtpCrawler</class>
  <method>crawl</method>
  <thread>11</thread>
  <message>Login to ftp://geoinformatics.nju.edu.cn ok:230 Logged on
</message>
</record>
<record>
  <date>2008-03-10T10:56:47</date>
  <millis>1205117807859</millis>
  <sequence>19</sequence>
  <logger>geoinformatics.nju.edu.cn</logger>
  <level>INFO</level>
  <class>ftp.FtpCrawler</class>
  <method>crawl</method>
  <thread>11</thread>
  <message>Finish crawling ftp://geoinformatics.nju.edu.cn</message>
</record>
<record>
  <date>2008-03-10T10:56:47</date>
  <millis>1205117807859</millis>
  <sequence>20</sequence>
  <logger>geoinformatics.nju.edu.cn</logger>
  <level>INFO</level>
  <class>ftp.FtpCrawler</class>
  <method>crawl</method>
  <thread>11</thread>
  <message>16 items are crawled</message>
</record>
</log>
